{
    "examples": {
        "VQSsequenceRepeat_gene_01": {
            "description": "### `CAG` repeat in the first exon of the huntingtin gene (HTT)\n\nFor details see above. \n\n#### Solution using `VQSsequenceRepeatRequest` with `geneId` and `sequenceLength`\n\nHere instead of the position simply the gene symbol is being used.",
            "request": {
                "geneId": "HTT",
                "repeatSubunitLength": 3,
                "requestProfile": "VQSsequenceRepeatRequest",
                "sequenceLength": [
                    105,
                    750
                ],
                "vrsType": "ReferenceLengthExpression"
            }
        },
        "VQSsequenceRepeat_gene_02": {
            "description": "### `CGG` trinucleotide repeat expansion in the FMR1 gene\n\nA `CGG` trinucleotide repeat expansion in the FMR1 gene on the X chromosome\n(Xq27.3) is known to cause Fragile X Syndrome (FXS). CGG repeating less than\n44 times are stable across generations.\n\n#### Solution using `VQSsequenceRepeatRequest` with `geneId` and `sequenceLength`\n\nSimilarly to the `HTT` example here a `geneId` is used to specify the gene\nand a range of sequence lengths is used to match against a `ReferenceLengthExpression`.",
            "request": {
                "geneId": "FMR1",
                "repeatSubunitLength": 3,
                "requestProfile": "VQSsequenceRepeatRequest",
                "sequenceLength": [
                    130,
                    600
                ],
                "vrsType": "ReferenceLengthExpression"
            }
        },
        "VQSsequenceRepeat_locus_01": {
            "description": "### `CAG` repeat in the first exon of the huntingtin gene (HTT)\n\nThe gene HTT is located at position 4p16.3. In individuals without Huntington's\ndisease, this CAG segment is typically repeated 10 to 35 times. Expansions\nbeyond 35 copys are associated with the development of Huntington's disease.\n\nExamples for query parameters are:    \n\n\n* GeneId: HTT   \n* referenceAccession: refseq:NC_000004.12   \n* start: 3074681    \n* end: 3243960    \n* RepeatSubunitLength: 3 (CAG)    \n* RepeatSubunitCount: [36, 250] (not yet defined in VRS or Beacon)    \n* SequenceLength:  [105, 750]    \n\nSee also the [genome browser material](https://genome.ucsc.edu/training/education/cag.html).\n\n#### Solution using `VQSsequenceRepeatRequest` with locus and `sequenceLength`\n\nThis example uses the HTT genome position and a range of (extended) sequence\nlengths to match against a `ReferenceLengthExpression` since the VRS v2 model\ndoes not contain a \"repeat count\" concept but only the overall length and\nunit length (as well as the sequence).\n\nTODO: Limit location to first exon?",
            "request": {
                "end": 3243960,
                "referenceAccession": "refseq:NC_000004.12",
                "repeatSubunitLength": 3,
                "requestProfile": "VQSsequenceRepeatRequest",
                "sequenceLength": [
                    105,
                    750
                ],
                "start": 3074681,
                "vrsType": "ReferenceLengthExpression"
            }
        }
    }
}